setup.py
kcwebsocket/__init__.py
kcwebsocket/rfdszbfnbxrdfgvxrhbdtxrhtbs.py
kcwebsocket.egg-info/PKG-INFO
kcwebsocket.egg-info/SOURCES.txt
kcwebsocket.egg-info/dependency_links.txt
kcwebsocket.egg-info/requires.txt
kcwebsocket.egg-info/top_level.txt