Metadata-Version: 1.2
Name: kcwebsocket
Version: 3.45
Summary: kcwebsocket
Home-page: UNKNOWN
Author: 百里
Author-email: kcwebs@kwebapp.cn
Maintainer: 坤坤
Maintainer-email: fk1402936534@qq.com
License: MIT License
Keywords: kcwebsocket3.45
Platform: UNKNOWN
